thinknet_variable_validator/__init__.py
thinknet_variable_validator/error_data.py
thinknet_variable_validator/validator.py
thinknet_variable_validator-1.0.0b4.dist-info/METADATA
thinknet_variable_validator-1.0.0b4.dist-info/WHEEL
thinknet_variable_validator-1.0.0b4.dist-info/top_level.txt
thinknet_variable_validator-1.0.0b4.dist-info/RECORD
