Metadata-Version: 2.4
Name: thinknet-variable-validator
Version: 1.0.0b4
Summary: Validate envs or any variable for data-eng@thinknet
Author-email: TN-DE Team <thinknet_dataengineer@thinknet.co.th>
Project-URL: Homepage, https://gitlab.thinknet.co.th/data-eng/library/variable-validator
Classifier: Intended Audience :: Developers
Classifier: Programming Language :: Python :: 3.8
Classifier: Programming Language :: Python :: 3.9
Classifier: Programming Language :: Python :: 3.10
Classifier: Programming Language :: Python :: 3.11
Classifier: Programming Language :: Python :: 3.12
Classifier: Development Status :: 4 - Beta
Classifier: Topic :: Software Development :: Libraries
Requires-Python: >=3.8
Requires-Dist: pytz>=2024.2
Requires-Dist: thinknet-application-specific-exception>=1.0.0rc0
Provides-Extra: dev
Requires-Dist: pytest; extra == "dev"
